MANIFEST.in
README.rst
setup.py
django_prospect.egg-info/PKG-INFO
django_prospect.egg-info/SOURCES.txt
django_prospect.egg-info/dependency_links.txt
django_prospect.egg-info/not-zip-safe
django_prospect.egg-info/requires.txt
django_prospect.egg-info/top_level.txt
prospect/__init__.py
prospect/admin.py
prospect/forms.py
prospect/models.py
prospect/tests.py
prospect/urls.py
prospect/utils.py
prospect/views.py
prospect/locale/fr/LC_MESSAGES/django.mo
prospect/locale/fr/LC_MESSAGES/django.po
prospect/migrations/0001_initial.py
prospect/migrations/0002_auto__del_field_prospect_surname__del_field_prospect_address__del_fiel.py
prospect/migrations/0003_auto__del_field_prospect_siret_number__add_field_prospect_siret_code.py
prospect/migrations/0004_auto__chg_field_prospect_phone_number__chg_field_prospect_field__chg_f.py
prospect/migrations/0005_auto__add_activity.py
prospect/migrations/0006_auto__chg_field_activity_datetime.py
prospect/migrations/0007_auto__chg_field_activity_datetime.py
prospect/migrations/0008_auto__chg_field_activity_duration.py
prospect/migrations/__init__.py
prospect/templates/prospect/activity/model_detail.html
prospect/templates/prospect/activity/model_list.html
prospect/templates/prospect/field/model_detail.html
prospect/templates/prospect/prospect/import.html
prospect/templates/prospect/prospect/import_result.html
prospect/templates/prospect/prospect/model_detail.html
prospect/templates/prospect/prospect/model_form.html
prospect/templates/prospect/prospect/model_list.html